rhkafka/__init__.py
rhkafka/client.py
rhkafka/client_async.py
rhkafka/cluster.py
rhkafka/codec.py
rhkafka/common.py
rhkafka/conn.py
rhkafka/context.py
rhkafka/errors.py
rhkafka/future.py
rhkafka/structs.py
rhkafka/util.py
rhkafka/version.py
rhkafka/consumer/__init__.py
rhkafka/consumer/base.py
rhkafka/consumer/fetcher.py
rhkafka/consumer/group.py
rhkafka/consumer/multiprocess.py
rhkafka/consumer/simple.py
rhkafka/consumer/subscription_state.py
rhkafka/coordinator/__init__.py
rhkafka/coordinator/base.py
rhkafka/coordinator/consumer.py
rhkafka/coordinator/heartbeat.py
rhkafka/coordinator/protocol.py
rhkafka/coordinator/assignors/__init__.py
rhkafka/coordinator/assignors/abstract.py
rhkafka/coordinator/assignors/range.py
rhkafka/coordinator/assignors/roundrobin.py
rhkafka/metrics/__init__.py
rhkafka/metrics/compound_stat.py
rhkafka/metrics/dict_reporter.py
rhkafka/metrics/kafka_metric.py
rhkafka/metrics/measurable.py
rhkafka/metrics/measurable_stat.py
rhkafka/metrics/metric_config.py
rhkafka/metrics/metric_name.py
rhkafka/metrics/metrics.py
rhkafka/metrics/metrics_reporter.py
rhkafka/metrics/quota.py
rhkafka/metrics/stat.py
rhkafka/metrics/stats/__init__.py
rhkafka/metrics/stats/avg.py
rhkafka/metrics/stats/count.py
rhkafka/metrics/stats/histogram.py
rhkafka/metrics/stats/max_stat.py
rhkafka/metrics/stats/min_stat.py
rhkafka/metrics/stats/percentile.py
rhkafka/metrics/stats/percentiles.py
rhkafka/metrics/stats/rate.py
rhkafka/metrics/stats/sampled_stat.py
rhkafka/metrics/stats/sensor.py
rhkafka/metrics/stats/total.py
rhkafka/partitioner/__init__.py
rhkafka/partitioner/base.py
rhkafka/partitioner/default.py
rhkafka/partitioner/hashed.py
rhkafka/partitioner/roundrobin.py
rhkafka/producer/__init__.py
rhkafka/producer/base.py
rhkafka/producer/buffer.py
rhkafka/producer/future.py
rhkafka/producer/kafka.py
rhkafka/producer/keyed.py
rhkafka/producer/record_accumulator.py
rhkafka/producer/sender.py
rhkafka/producer/simple.py
rhkafka/protocol/__init__.py
robinhood_kafka_python-1.4.3.dist-info/LICENSE
robinhood_kafka_python-1.4.3.dist-info/METADATA
robinhood_kafka_python-1.4.3.dist-info/WHEEL
robinhood_kafka_python-1.4.3.dist-info/top_level.txt
robinhood_kafka_python-1.4.3.dist-info/RECORD
